MsFCoppel/Base.py
MsFCoppel/ColorJson.py
MsFCoppel/ErrorMs.py
MsFCoppel/Fork.py
MsFCoppel/ForkHttp.py
MsFCoppel/HttpErrors.py
MsFCoppel/HttpResponse.py
MsFCoppel/HttpTransit.py
MsFCoppel/LogssBottle.py
MsFCoppel/MsManager.py
MsFCoppel/NatsBase.py
MsFCoppel/Util.py
MsFCoppel/Worker.py
MsFCoppel/__init__.py
MsFCoppel/http_server.py
MsFCoppel/loggs.py
MsFCoppel/loggsWrapper.py
MsFCoppel/microservices.py
MsFCoppel/ms_base.py
MsFCoppel/options.py
MsFCoppel/types.py
MsFCoppel/version_framework.py
MsPPCoppel/Base.py
MsPPCoppel/ColorJson.py
MsPPCoppel/ErrorMs.py
MsPPCoppel/Fork.py
MsPPCoppel/ForkHttp.py
MsPPCoppel/HttpErrors.py
MsPPCoppel/HttpResponse.py
MsPPCoppel/HttpTransit.py
MsPPCoppel/LogssBottle.py
MsPPCoppel/MsManager.py
MsPPCoppel/NatsBase.py
MsPPCoppel/Util.py
MsPPCoppel/Worker.py
MsPPCoppel/__init__.py
MsPPCoppel/http_server.py
MsPPCoppel/loggs.py
MsPPCoppel/loggsWrapper.py
MsPPCoppel/microservices.py
MsPPCoppel/ms_base.py
MsPPCoppel/options.py
MsPPCoppel/types.py
MsPPCoppel/version_framework.py
msppcoppel-1.0.2.dist-info/METADATA
msppcoppel-1.0.2.dist-info/WHEEL
msppcoppel-1.0.2.dist-info/top_level.txt
msppcoppel-1.0.2.dist-info/RECORD
